excalibur
tests
