Metadata-Version: 1.1
Name: excalibur
Version: 1.0.9
Summary: A tool to manage plugins
Home-page: https://github.com/unistra/excalibur
Author: di-dip-unistra
Author-email: di-dip@unistra.fr
License: PSF
Download-URL: http://pypi.python.org/pypi/excalibur
Keywords: plugins,yaml,parser
Platform: UNKNOWN
Classifier: Development Status :: 3 - Alpha
Classifier: Intended Audience :: Developers
Classifier: License :: OSI Approved :: BSD License
Classifier: Operating System :: OS Independent
Classifier: Programming Language :: Python :: 2.7
Classifier: Programming Language :: Python :: 3.3
Classifier: Programming Language :: Python :: 3.4
